tests/__init__.py
tests/test_context.py
tests/test_dispatch.py
tests/test_pluggable.py
wraptools/__init__.py
wraptools/context.py
wraptools/dispatch.py
wraptools/pluggable.py
wraptools/contrib/__init__.py
wraptools/contrib/django/__init__.py
wraptools/contrib/django/dispatchers.py
wraptools-1.1.dist-info/DESCRIPTION.rst
wraptools-1.1.dist-info/LICENSE.txt
wraptools-1.1.dist-info/METADATA
wraptools-1.1.dist-info/RECORD
wraptools-1.1.dist-info/WHEEL
wraptools-1.1.dist-info/metadata.json
wraptools-1.1.dist-info/top_level.txt
