Metadata-Version: 2.0
Name: wraptools
Version: 1.1
Summary: Utilities for wrapping and dispatching functions
Home-page: https://github.com/hirokiky/wraptools/
Author: Hiroki Kiyohara
Author-email: hirokiky@gmail.com
License: MIT
Platform: UNKNOWN
